iot_api_poller/__init__.py
iot_api_poller/iotApiPoller.py
iot_api_poller/main.py
iot_api_poller-0.10.dist-info/LICENSE
iot_api_poller-0.10.dist-info/METADATA
iot_api_poller-0.10.dist-info/WHEEL
iot_api_poller-0.10.dist-info/top_level.txt
iot_api_poller-0.10.dist-info/RECORD
