Metadata-Version: 2.1
Name: iot-api-poller
Version: 0.10
Summary: Polling app that fetches data from IoT hubs
Home-page: https://github.com/AnnAnnFryingPan/iot_api_poller
Author: Ann Gledson
Author-email: anngledson@gmail.com
License: MIT
Platform: UNKNOWN
Requires-Dist: certifi
Requires-Dist: chardet
Requires-Dist: data-hub-call
Requires-Dist: idna
Requires-Dist: scheduled-poller
Requires-Dist: python-dateutil
Requires-Dist: requests
Requires-Dist: six
Requires-Dist: urllib3
